{
  "colorPalette": "electric-blue",
  "glassSurfaces": true,
  "entries": [
    {
      "id": "20260401-171111-b12d",
      "title": "Reven The Big Show",
      "commanders": [
        "Reven The Big Show"
      ],
      "dateStart": "2026-04-02T00:11:11.000Z",
      "dateEnd": "2026-04-02T01:49:41.000Z",
      "dateLabel": "4/1/2026, 5:11:11 PM - 4/1/2026, 6:49:41 PM",
      "url": "https://the-agg.github.io/alliance-fight-reports/?report=20260401-171111-b12d",
      "summary": {
        "borderlandsPct": 1,
        "mapSlices": [
          {
            "name": "Red Borderlands",
            "value": 8,
            "color": "#ef4444"
          },
          {
            "name": "Green Borderlands",
            "value": 2,
            "color": "#22c55e"
          },
          {
            "name": "Blue Borderlands",
            "value": 2,
            "color": "#3b82f6"
          }
        ],
        "avgSquadSize": 40,
        "avgEnemySize": 39
      }
    },
    {
      "id": "20260325-170648-fql5",
      "title": "Fíbbs",
      "commanders": [
        "Fíbbs"
      ],
      "dateStart": "2026-03-26T00:06:48.000Z",
      "dateEnd": "2026-03-26T01:51:05.000Z",
      "dateLabel": "3/25/2026, 5:06:48 PM - 3/25/2026, 6:51:05 PM",
      "url": "https://the-agg.github.io/alliance-fight-reports/?report=20260325-170648-fql5",
      "summary": {
        "borderlandsPct": 1,
        "mapSlices": [
          {
            "name": "Blue Borderlands",
            "value": 28,
            "color": "#3b82f6"
          }
        ],
        "avgSquadSize": 43,
        "avgEnemySize": 45
      }
    },
    {
      "id": "20260317-185332-988h",
      "title": "Undie Vided",
      "commanders": [
        "Undie Vided"
      ],
      "dateStart": "2026-03-18T01:53:32.000Z",
      "dateEnd": "2026-03-18T03:01:53.000Z",
      "dateLabel": "3/17/2026, 6:53:32 PM - 3/17/2026, 8:01:53 PM",
      "url": "https://the-agg.github.io/alliance-fight-reports/?report=20260317-185332-988h",
      "summary": {
        "borderlandsPct": 0,
        "mapSlices": [
          {
            "name": "Edge of the Mists",
            "value": 21,
            "color": "#64748b"
          }
        ],
        "avgSquadSize": 11,
        "avgEnemySize": 12
      }
    },
    {
      "id": "20260317-185332-8un4",
      "title": "Rizem Withthe Tizim",
      "commanders": [
        "Rizem Withthe Tizim"
      ],
      "dateStart": "2026-03-18T01:53:32.000Z",
      "dateEnd": "2026-03-18T03:01:54.000Z",
      "dateLabel": "3/17/2026, 6:53:32 PM - 3/17/2026, 8:01:54 PM",
      "url": "https://the-agg.github.io/alliance-fight-reports/?report=20260317-185332-8un4",
      "summary": {
        "borderlandsPct": 0,
        "mapSlices": [
          {
            "name": "Edge of the Mists",
            "value": 23,
            "color": "#64748b"
          }
        ],
        "avgSquadSize": 12,
        "avgEnemySize": 10
      }
    },
    {
      "id": "20260313-190942-zy9g",
      "title": "Hârâshô",
      "commanders": [
        "Hârâshô"
      ],
      "dateStart": "2026-03-14T02:09:42.000Z",
      "dateEnd": "2026-03-14T03:51:26.000Z",
      "dateLabel": "3/13/2026, 7:09:42 PM - 3/13/2026, 8:51:26 PM",
      "url": "https://the-agg.github.io/alliance-fight-reports/?report=20260313-190942-zy9g",
      "summary": {
        "borderlandsPct": 1,
        "mapSlices": [
          {
            "name": "Green Borderlands",
            "value": 11,
            "color": "#22c55e"
          }
        ],
        "avgSquadSize": 49,
        "avgEnemySize": 33
      }
    },
    {
      "id": "20260310-170310-hiyj",
      "title": "Lightspeed Jack",
      "commanders": [
        "Lightspeed Jack"
      ],
      "dateStart": "2026-03-11T00:03:10.000Z",
      "dateEnd": "2026-03-11T00:23:23.000Z",
      "dateLabel": "3/10/2026, 5:03:10 PM - 3/10/2026, 5:23:23 PM",
      "url": "https://the-agg.github.io/alliance-fight-reports/?report=20260310-170310-hiyj",
      "summary": {
        "borderlandsPct": 1,
        "mapSlices": [
          {
            "name": "Green Borderlands",
            "value": 5,
            "color": "#22c55e"
          }
        ],
        "avgSquadSize": 31,
        "avgEnemySize": 47
      }
    },
    {
      "id": "20260308-164749-rt5r",
      "title": "Lightspeed Jack",
      "commanders": [
        "Lightspeed Jack"
      ],
      "dateStart": "2026-03-08T23:47:49.000Z",
      "dateEnd": "2026-03-09T02:03:18.000Z",
      "dateLabel": "3/8/2026, 4:47:49 PM - 3/8/2026, 7:03:18 PM",
      "url": "https://the-agg.github.io/alliance-fight-reports/?report=20260308-164749-rt5r",
      "summary": {
        "borderlandsPct": 1,
        "mapSlices": [
          {
            "name": "Green Borderlands",
            "value": 20,
            "color": "#22c55e"
          }
        ],
        "avgSquadSize": 34,
        "avgEnemySize": 41
      }
    },
    {
      "id": "20260307-111433-j6b0",
      "title": "Viktor Kas",
      "commanders": [
        "Viktor Kas"
      ],
      "dateStart": "2026-03-07T19:14:33.000Z",
      "dateEnd": "2026-03-07T20:05:42.000Z",
      "dateLabel": "3/7/2026, 11:14:33 AM - 3/7/2026, 12:05:42 PM",
      "url": "https://the-agg.github.io/alliance-fight-reports/?report=20260307-111433-j6b0",
      "summary": {
        "borderlandsPct": 0,
        "mapSlices": [
          {
            "name": "Eternal Battlegrounds",
            "value": 24,
            "color": "#ffffff"
          }
        ],
        "avgSquadSize": 7,
        "avgEnemySize": 17
      }
    },
    {
      "id": "20260301-210149-q7cv",
      "title": "Lightspeed Jack",
      "commanders": [
        "Lightspeed Jack"
      ],
      "dateStart": "2026-03-02T05:01:49.000Z",
      "dateEnd": "2026-03-02T06:17:14.000Z",
      "dateLabel": "3/1/2026, 9:01:49 PM - 3/1/2026, 10:17:14 PM",
      "url": "https://the-agg.github.io/alliance-fight-reports/?report=20260301-210149-q7cv",
      "summary": {
        "borderlandsPct": 1,
        "mapSlices": [
          {
            "name": "Red Borderlands",
            "value": 7,
            "color": "#ef4444"
          },
          {
            "name": "Green Borderlands",
            "value": 2,
            "color": "#22c55e"
          }
        ],
        "avgSquadSize": 31,
        "avgEnemySize": 30
      }
    }
  ]
}